{"type":"urn:miot-spec-v2:device:treadmill:0000A035:asp-a9:1","description":"Treadmill","services":[{"iid":1,"type":"urn:miot-spec-v2:service:device-information:00007801:asp-a9:1","description":"Device Information","properties":[{"iid":1,"type":"urn:miot-spec-v2:property:manufacturer:00000001:asp-a9:1","description":"Device Manufacturer","format":"string","access":["read"]},{"iid":2,"type":"urn:miot-spec-v2:property:model:00000002:asp-a9:1","description":"Device Model","format":"string","access":["read"]},{"iid":3,"type":"urn:miot-spec-v2:property:serial-number:00000003:asp-a9:1","description":"Device ID","format":"string","access":["read"]},{"iid":4,"type":"urn:miot-spec-v2:property:firmware-revision:00000005:asp-a9:1","description":"Current Firmware Version","format":"string","access":["read"]},{"iid":5,"type":"urn:miot-spec-v2:property:serial-no:000000FF:asp-a9:1","description":"Serial Number","format":"string","access":["read","notify"]}]},{"iid":2,"type":"urn:miot-spec-v2:service:treadmill:00007851:asp-a9:1","description":"Treadmill","properties":[{"iid":1,"type":"urn:miot-spec-v2:property:on:00000006:asp-a9:1","description":"Switch Status","format":"bool","access":["read","write","notify"]},{"iid":2,"type":"urn:miot-spec-v2:property:fault:00000009:asp-a9:1","description":"Device Fault","format":"uint8","access":["read","notify"],"value-list":[{"value":0,"description":"No Faults"}]},{"iid":3,"type":"urn:miot-spec-v2:property:speed-level:00000023:asp-a9:1","description":"Speed Level","format":"uint8","access":["read","write","notify"],"value-range":[0,140,1]},{"iid":4,"type":"urn:miot-spec-v2:property:status:00000007:asp-a9:1","description":"Status","format":"uint8","access":["read","notify"],"value-list":[{"value":0,"description":"Idle"},{"value":2,"description":"Busy"},{"value":1,"description":"Sleep"}]},{"iid":8,"type":"urn:miot-spec-v2:property:current-distance:00000075:asp-a9:1","description":"Current Distance","format":"uint32","access":["read","notify"],"value-range":[0,5000,1]},{"iid":11,"type":"urn:miot-spec-v2:property:working-time:00000079:asp-a9:1","description":"Working Time","format":"uint32","access":["read","notify"],"unit":"seconds","value-range":[0,100000000,1]},{"iid":14,"type":"urn:miot-spec-v2:property:current-calorie-consumption:0000007A:asp-a9:1","description":"Current Calorie Consumption","format":"uint32","access":["read","notify"],"value-range":[0,1000000,1]},{"iid":17,"type":"urn:miot-spec-v2:property:current-step-count:0000007B:asp-a9:1","description":"Current Step Count","format":"uint32","access":["read","notify"],"value-range":[0,10000,1]},{"iid":18,"type":"urn:miot-spec-v2:property:left-step-count:000000F8:asp-a9:1","description":"Left Step Count","format":"uint16","access":["read","notify"],"value-range":[0,1000,1]}],"actions":[{"iid":1,"type":"urn:miot-spec-v2:action:start-work:00002827:asp-a9:1","description":"Start Work","in":[],"out":[]},{"iid":2,"type":"urn:miot-spec-v2:action:pause:0000280C:asp-a9:1","description":"Pause","in":[],"out":[]},{"iid":3,"type":"urn:miot-spec-v2:action:stop-working:00002825:asp-a9:1","description":"Stop Working","in":[],"out":[]}]}]}