{"type":"urn:miot-spec-v2:device:projector:0000A02C:h2t-projet:1","description":"Projector","services":[{"iid":1,"type":"urn:miot-spec-v2:service:device-information:00007801:h2t-projet:1","description":"Device Information","properties":[{"iid":1,"type":"urn:miot-spec-v2:property:manufacturer:00000001:h2t-projet:1","description":"Device Manufacturer","format":"string","access":["read"]},{"iid":2,"type":"urn:miot-spec-v2:property:model:00000002:h2t-projet:1","description":"Device Model","format":"string","access":["read"]},{"iid":3,"type":"urn:miot-spec-v2:property:serial-number:00000003:h2t-projet:1","description":"Device Serial Number","format":"string","access":["read"]},{"iid":4,"type":"urn:miot-spec-v2:property:firmware-revision:00000005:h2t-projet:1","description":"Current Firmware Version","format":"string","access":["read"]}]},{"iid":2,"type":"urn:miot-spec-v2:service:projector:00007840:h2t-projet:1","description":"Projector","properties":[{"iid":1,"type":"urn:miot-spec-v2:property:on:00000006:h2t-projet:1","description":"Switch Status","format":"bool","access":["read","write","notify"]}],"actions":[{"iid":1,"type":"urn:miot-spec-v2:action:turn-off:00002809:h2t-projet:1","description":"Turn Off","in":[],"out":[]},{"iid":2,"type":"urn:miot-spec-v2:action:turn-on:00002808:h2t-projet:1","description":"Turn On","in":[],"out":[]}]}]}