{"type":"urn:miot-spec-v2:device:bath-heater:0000A028:youpon-yb0a01:1","description":"Bath Heater","services":[{"iid":1,"type":"urn:miot-spec-v2:service:device-information:00007801:youpon-yb0a01:1","description":"Device Information","properties":[{"iid":1,"type":"urn:miot-spec-v2:property:manufacturer:00000001:youpon-yb0a01:1","description":"Device Manufacturer","format":"string","access":["read"]},{"iid":2,"type":"urn:miot-spec-v2:property:model:00000002:youpon-yb0a01:1","description":"Device Model","format":"string","access":["read"]},{"iid":3,"type":"urn:miot-spec-v2:property:serial-number:00000003:youpon-yb0a01:1","description":"Device ID","format":"string","access":["read"]},{"iid":4,"type":"urn:miot-spec-v2:property:firmware-revision:00000005:youpon-yb0a01:1","description":"Current Firmware Version","format":"string","access":["read"]},{"iid":5,"type":"urn:miot-spec-v2:property:serial-no:000000FF:youpon-yb0a01:1","description":"Serial Number","format":"string","access":["read","notify"]}]},{"iid":2,"type":"urn:miot-spec-v2:service:light:00007802:youpon-yb0a01:1","description":"Light","properties":[{"iid":1,"type":"urn:miot-spec-v2:property:on:00000006:youpon-yb0a01:1","description":"Switch Status","format":"bool","access":["read","write","notify"]},{"iid":2,"type":"urn:miot-spec-v2:property:on:00000006:youpon-yb0a01:1","description":"Switch Status","format":"bool","access":["read","write","notify"]}]},{"iid":3,"type":"urn:miot-spec-v2:service:ptc-bath-heater:0000783B:youpon-yb0a01:1","description":"PTC Bath Heater","properties":[{"iid":1,"type":"urn:miot-spec-v2:property:fault:00000009:youpon-yb0a01:1","description":"Device Fault","format":"uint8","access":["read","notify"],"value-list":[{"value":0,"description":"No Faults"},{"value":1,"description":"Temperature Sensor"},{"value":2,"description":"Control Communication"},{"value":3,"description":"Display Communication"}]},{"iid":2,"type":"urn:miot-spec-v2:property:mode:00000008:youpon-yb0a01:1","description":"Mode","format":"uint8","access":["read","write","notify"],"value-list":[{"value":0,"description":"Idle"},{"value":1,"description":"Heat"},{"value":2,"description":"Heat2"},{"value":3,"description":"Ventilate"},{"value":4,"description":"Dry2"},{"value":5,"description":"Dry"},{"value":6,"description":"Sterilization"}]}],"actions":[{"iid":1,"type":"urn:miot-spec-v2:action:stop-working:00002825:youpon-yb0a01:1","description":"Stop Working","in":[],"out":[]}]},{"iid":4,"type":"urn:youpon-spec:service:swing:00007801:youpon-yb0a01:1","description":"swing","properties":[{"iid":1,"type":"urn:youpon-spec:property:on:00000001:youpon-yb0a01:1","description":"on","format":"bool","access":["read","write","notify"]}]},{"iid":5,"type":"urn:youpon-spec:service:professional-setting:00007802:youpon-yb0a01:1","description":"professional-setting","properties":[{"iid":1,"type":"urn:youpon-spec:property:type:00000001:youpon-yb0a01:1","description":"type","format":"uint8","access":["read","notify"],"value-list":[{"value":0,"description":"Nine-key"},{"value":1,"description":"Seven-key"}]}]}]}