{"type":"urn:miot-spec-v2:device:air-purifier:0000A007:zhimi-vb2:1","description":"Air Purifier","services":[{"iid":2,"type":"urn:miot-spec-v2:service:air-purifier:00007811:zhimi-vb2:1","description":"Air Purifier","properties":[{"iid":1,"type":"urn:miot-spec-v2:property:fault:00000009:zhimi-vb2:1","description":"Device Fault","format":"uint8","access":["read","notify"],"value-list":[{"value":0,"description":"No faults"},{"value":1,"description":"m1_run"},{"value":2,"description":"m1_stuck"},{"value":3,"description":"no_sensor"},{"value":4,"description":"error_hum"},{"value":5,"description":"error_temp"},{"value":6,"description":"timer_error1"},{"value":7,"description":"timer_error2"}]},{"iid":2,"type":"urn:miot-spec-v2:property:on:00000006:zhimi-vb2:1","description":"Switch Status","format":"bool","access":["read","write","notify"]},{"iid":4,"type":"urn:miot-spec-v2:property:fan-level:00000016:zhimi-vb2:1","description":"Fan Level","format":"uint8","access":["read","write","notify"],"value-list":[{"value":1,"description":"Level1"},{"value":2,"description":"Level2"},{"value":3,"description":"Level3"},{"value":0,"description":"Sleep"}]},{"iid":5,"type":"urn:miot-spec-v2:property:mode:00000008:zhimi-vb2:1","description":"Mode","format":"uint8","access":["read","write","notify"],"value-list":[{"value":0,"description":"Auto"},{"value":1,"description":"Sleep"},{"value":2,"description":"Favorite"},{"value":3,"description":"None"}]}]},{"iid":1,"type":"urn:miot-spec-v2:service:device-information:00007801:zhimi-vb2:1","description":"Device Information","properties":[{"iid":4,"type":"urn:miot-spec-v2:property:firmware-revision:00000005:zhimi-vb2:1","description":"Current Firmware Version","format":"string","access":["read"]},{"iid":1,"type":"urn:miot-spec-v2:property:manufacturer:00000001:zhimi-vb2:1","description":"Device Manufacturer","format":"string","access":["read"]},{"iid":2,"type":"urn:miot-spec-v2:property:model:00000002:zhimi-vb2:1","description":"Device Model","format":"string","access":["read"]},{"iid":3,"type":"urn:miot-spec-v2:property:serial-number:00000003:zhimi-vb2:1","description":"Device Serial Number","format":"string","access":["read"]}]},{"iid":3,"type":"urn:miot-spec-v2:service:environment:0000780A:zhimi-vb2:1","description":"Environment","properties":[{"iid":6,"type":"urn:miot-spec-v2:property:pm2.5-density:00000034:zhimi-vb2:1","description":"PM2.5 Density","format":"float","access":["read","notify"],"value-range":[0,600,1]},{"iid":7,"type":"urn:miot-spec-v2:property:relative-humidity:0000000C:zhimi-vb2:1","description":"Relative Humidity","format":"uint8","access":["read","notify"],"unit":"percentage","value-range":[0,100,1]},{"iid":8,"type":"urn:miot-spec-v2:property:temperature:00000020:zhimi-vb2:1","description":"Temperature","format":"float","access":["read","notify"],"value-range":[-40,125,0.1]}]},{"iid":4,"type":"urn:miot-spec-v2:service:filter:0000780B:zhimi-vb2:1","description":"Filter","properties":[{"iid":3,"type":"urn:miot-spec-v2:property:filter-life-level:0000001E:zhimi-vb2:1","description":"Filter Life Level","format":"uint8","access":["read","notify"],"unit":"percentage","value-range":[0,100,1]},{"iid":5,"type":"urn:miot-spec-v2:property:filter-used-time:00000048:zhimi-vb2:1","description":"Filter Used Time","format":"uint16","access":["read","notify"],"unit":"hours","value-range":[0,18000,1]}]},{"iid":5,"type":"urn:miot-spec-v2:service:alarm:00007804:zhimi-vb2:1","description":"Alarm","properties":[{"iid":1,"type":"urn:miot-spec-v2:property:alarm:00000012:zhimi-vb2:1","description":"Alarm","format":"bool","access":["read","write","notify"]},{"iid":2,"type":"urn:miot-spec-v2:property:volume:00000013:zhimi-vb2:1","description":"Volume","format":"uint8","access":["read","write","notify"],"unit":"percentage","value-range":[0,100,1]}]},{"iid":6,"type":"urn:miot-spec-v2:service:indicator-light:00007803:zhimi-vb2:1","description":"Indicator Light","properties":[{"iid":1,"type":"urn:miot-spec-v2:property:brightness:0000000D:zhimi-vb2:1","description":"Brightness","format":"uint8","access":["read","write","notify"],"value-list":[{"value":0,"description":"brightest"},{"value":1,"description":"glimmer"},{"value":2,"description":"not bright"}]},{"iid":6,"type":"urn:miot-spec-v2:property:on:00000006:zhimi-vb2:1","description":"Switch Status","format":"bool","access":["read","write","notify"]}]},{"iid":7,"type":"urn:miot-spec-v2:service:physical-controls-locked:00007807:zhimi-vb2:1","description":"Physical Control Locked","properties":[{"iid":1,"type":"urn:miot-spec-v2:property:physical-controls-locked:0000001D:zhimi-vb2:1","description":"Physical Control Locked","format":"bool","access":["read","write","notify"]}]},{"iid":8,"type":"urn:zhimi-spec:service:button:00000001:zhimi-vb2:1","description":"button","properties":[{"iid":1,"type":"urn:zhimi-spec:property:button-pressed:00000002:zhimi-vb2:1","description":"button_pressed","format":"string","access":["read"]}],"actions":[{"iid":1,"type":"urn:zhimi-spec:action:toggle:00000028:zhimi-vb2:1","description":"toggle","in":[],"out":[]},{"iid":2,"type":"urn:zhimi-spec:action:toggle-mode:00000029:zhimi-vb2:1","description":"toggle-mode","in":[],"out":[]}],"events":[{"iid":1,"type":"urn:zhimi-spec:event:child-lock-trigger:00000031:zhimi-vb2:1","description":"child-lock-trigger","arguments":[1]}]},{"iid":9,"type":"urn:zhimi-spec:service:filter-time:00000003:zhimi-vb2:1","description":"filter-time","properties":[{"iid":1,"type":"urn:zhimi-spec:property:filter-max-time:00000004:zhimi-vb2:1","description":"filter-max-time","format":"int32","access":["read","write"],"unit":"hours","value-range":[2000,8000,1]},{"iid":2,"type":"urn:zhimi-spec:property:filter-hour-used-debug:00000046:zhimi-vb2:1","description":"","format":"int32","access":["read","write"],"unit":"hours","value-range":[0,18000,1]}],"events":[{"iid":1,"type":"urn:zhimi-spec:event:filter1-eof:0000002C:zhimi-vb2:1","description":"filter1-eof","arguments":[1]},{"iid":2,"type":"urn:zhimi-spec:event:filter-door-opened:0000002D:zhimi-vb2:1","description":"filter-door-opened","arguments":[1]},{"iid":3,"type":"urn:zhimi-spec:event:reset-filter-life:0000002E:zhimi-vb2:1","description":"reset-filter-life","arguments":[1]}]},{"iid":10,"type":"urn:zhimi-spec:service:motor-speed:00000005:zhimi-vb2:1","description":"motor-speed","properties":[{"iid":1,"type":"urn:zhimi-spec:property:m1-strong:00000006:zhimi-vb2:1","description":"m1-strong","format":"int32","access":["read","write"],"value-range":[300,2300,10]},{"iid":2,"type":"urn:zhimi-spec:property:m1-high:00000007:zhimi-vb2:1","description":"m1-high","format":"int32","access":["read","write"],"value-range":[300,2300,10]},{"iid":3,"type":"urn:zhimi-spec:property:m1-med:00000008:zhimi-vb2:1","description":"m1-med","format":"int32","access":["read","write"],"value-range":[300,2300,10]},{"iid":4,"type":"urn:zhimi-spec:property:m1-med-l:00000009:zhimi-vb2:1","description":"m1-med-l","format":"int32","access":["read","write"],"value-range":[300,2300,10]},{"iid":5,"type":"urn:zhimi-spec:property:m1-low:0000000A:zhimi-vb2:1","description":"m1-low","format":"int32","access":["read","write"],"value-range":[300,2300,10]},{"iid":6,"type":"urn:zhimi-spec:property:m1-silent:0000000B:zhimi-vb2:1","description":"m1-silent","format":"int32","access":["read","write"],"value-range":[300,2300,10]},{"iid":7,"type":"urn:zhimi-spec:property:m1-favorite:0000000C:zhimi-vb2:1","description":"m1-favorite","format":"int32","access":["read"],"value-range":[300,2300,10]},{"iid":8,"type":"urn:zhimi-spec:property:motor1-speed:0000000D:zhimi-vb2:1","description":"motor1-speed","format":"int32","access":["read"],"value-range":[0,10000,1]},{"iid":9,"type":"urn:zhimi-spec:property:motor1-set-speed:00000041:zhimi-vb2:1","description":"motor1-set-speed","format":"int32","access":["read"],"value-range":[0,10000,1]},{"iid":10,"type":"urn:zhimi-spec:property:favorite-level:00000045:zhimi-vb2:1","description":"favorite-level","format":"int32","access":["read","write"],"value-range":[0,9,1]}]},{"iid":12,"type":"urn:zhimi-spec:service:use-time:00000013:zhimi-vb2:1","description":"use-time","properties":[{"iid":1,"type":"urn:zhimi-spec:property:use-time:00000014:zhimi-vb2:1","description":"use-time","format":"int32","access":["read"],"unit":"seconds","value-range":[0,2147483647,1]}]},{"iid":13,"type":"urn:zhimi-spec:service:aqi:00000015:zhimi-vb2:1","description":"aqi","properties":[{"iid":1,"type":"urn:zhimi-spec:property:purify-volume:00000016:zhimi-vb2:1","description":"purify-volume","format":"int32","access":["read"],"value-range":[0,2147483647,1]},{"iid":2,"type":"urn:zhimi-spec:property:average-aqi:00000017:zhimi-vb2:1","description":"average-aqi","format":"int32","access":["read"],"value-range":[0,600,1]},{"iid":3,"type":"urn:zhimi-spec:property:average-aqi-cnt:00000018:zhimi-vb2:1","description":"average_aqi read times","format":"int32","access":["read"],"value-range":[0,2147483647,1]},{"iid":4,"type":"urn:zhimi-spec:property:aqi-zone:00000019:zhimi-vb2:1","description":"aqi-zone","format":"string","access":["read"]},{"iid":5,"type":"urn:zhimi-spec:property:sensor-state:00000020:zhimi-vb2:1","description":"sensor-state","format":"int32","access":["read"],"value-list":[{"value":0,"description":"waiting"},{"value":1,"description":"ready"}]},{"iid":6,"type":"urn:zhimi-spec:property:aqi-goodh:00000034:zhimi-vb2:1","description":"aqi-goodh","format":"int32","access":["read","write"],"value-range":[0,255,1]},{"iid":7,"type":"urn:zhimi-spec:property:aqi-runstate:00000035:zhimi-vb2:1","description":"runstate","format":"int32","access":["read"],"value-list":[{"value":0,"description":"continue"},{"value":1,"description":"hold"},{"value":2,"description":"sleep"}]},{"iid":8,"type":"urn:zhimi-spec:property:aqi-state:00000036:zhimi-vb2:1","description":"aqi-state","format":"int32","access":["read"],"value-list":[{"value":0,"description":"AQI_GOOD_L"},{"value":1,"description":"AQI_GOOD_H"},{"value":2,"description":"AQI_MID_L"},{"value":3,"description":"AQI_MID_H"},{"value":4,"description":"AQI_BAD_L"},{"value":5,"description":"AQI_BAD_H"}]},{"iid":9,"type":"urn:zhimi-spec:property:aqi-updata-heartbeat:00000001:zhimi-vb2:1","description":"aqi-updata-heartbeat","format":"uint16","access":["write"],"unit":"seconds","value-range":[0,65535,1]}]},{"iid":14,"type":"urn:zhimi-spec:service:rfid:0000001A:zhimi-vb2:1","description":"rfid","properties":[{"iid":1,"type":"urn:zhimi-spec:property:rfid-tag:0000001B:zhimi-vb2:1","description":"rfid-tag","format":"string","access":["read"]},{"iid":2,"type":"urn:zhimi-spec:property:rfid-factory-id:0000001C:zhimi-vb2:1","description":"rfid-factory-id","format":"string","access":["read"]},{"iid":3,"type":"urn:zhimi-spec:property:rfid-product-id:0000001D:zhimi-vb2:1","description":"rfid-product-id","format":"string","access":["read"]},{"iid":4,"type":"urn:zhimi-spec:property:rfid-time:0000001E:zhimi-vb2:1","description":"rfid-time","format":"string","access":["read"]},{"iid":5,"type":"urn:zhimi-spec:property:rfid-serial-num:0000001F:zhimi-vb2:1","description":"rfid-serial-num","format":"string","access":["read"]}]},{"iid":15,"type":"urn:zhimi-spec:service:others:00000021:zhimi-vb2:1","description":"others","properties":[{"iid":1,"type":"urn:zhimi-spec:property:app-extra:00000022:zhimi-vb2:1","description":"app-extra","format":"int32","access":["read","write"],"value-range":[0,2147483647,1]},{"iid":2,"type":"urn:zhimi-spec:property:main-channel:00000023:zhimi-vb2:1","description":"main-channel","format":"int32","access":["read"],"value-range":[0,2147483647,1]},{"iid":3,"type":"urn:zhimi-spec:property:slave-channel:00000024:zhimi-vb2:1","description":"slave-channel","format":"int32","access":["read"],"value-range":[0,2147483647,1]},{"iid":4,"type":"urn:zhimi-spec:property:cola:00000025:zhimi-vb2:1","description":"cola","format":"string","access":["read","write"]},{"iid":5,"type":"urn:zhimi-spec:property:buttom-door:00000037:zhimi-vb2:1","description":"buttom-door","format":"string","access":["read"]},{"iid":6,"type":"urn:zhimi-spec:property:reboot-cause:00000043:zhimi-vb2:1","description":"reboot_cause","format":"int32","access":["read"],"value-list":[{"value":0,"description":"REASON_HW_BOOT"},{"value":1,"description":"REASON_USER_REBOOT"},{"value":2,"description":"REASON_UPDATE"},{"value":3,"description":"REASON_WDT"}]},{"iid":7,"type":"urn:zhimi-spec:property:manual-level:00000047:zhimi-vb2:1","description":"manual-level","format":"int32","access":["read"],"value-list":[{"value":1,"description":"level1"},{"value":2,"description":"level2"},{"value":3,"description":"level3"}]},{"iid":8,"type":"urn:zhimi-spec:property:powertime:00000049:zhimi-vb2:1","description":"powertime","format":"int32","access":["read"],"value-range":[0,2147483647,1]},{"iid":9,"type":"urn:zhimi-spec:property:country-code:00000001:zhimi-vb2:1","description":"country-code","format":"int32","access":["read","notify","write"],"unit":"none","value-list":[{"value":91,"description":"印度"},{"value":44,"description":"分销英文"},{"value":852,"description":"中国香港"},{"value":886,"description":"中国台湾"},{"value":82,"description":"韩国"}]}],"events":[{"iid":1,"type":"urn:zhimi-spec:event:status-report:00000042:zhimi-vb2:1","description":"status-report","arguments":[1]}]}]}