{"type":"urn:miot-spec-v2:device:massage:0000A018:rotai-rt6920:1","description":"Massage","services":[{"iid":1,"type":"urn:miot-spec-v2:service:device-information:00007801:rotai-rt6920:1","description":"Device Information","properties":[{"iid":1,"type":"urn:miot-spec-v2:property:manufacturer:00000001:rotai-rt6920:1","description":"Device Manufacturer","format":"string","access":["read"]},{"iid":2,"type":"urn:miot-spec-v2:property:model:00000002:rotai-rt6920:1","description":"Device Model","format":"string","access":["read"]},{"iid":3,"type":"urn:miot-spec-v2:property:serial-number:00000003:rotai-rt6920:1","description":"Device Serial Number","format":"string","access":["read"]},{"iid":4,"type":"urn:miot-spec-v2:property:firmware-revision:00000005:rotai-rt6920:1","description":"Current Firmware Version","format":"string","access":["read"]}]},{"iid":2,"type":"urn:miot-spec-v2:service:massage:00007829:rotai-rt6920:1","description":"Massage","properties":[{"iid":1,"type":"urn:miot-spec-v2:property:on:00000006:rotai-rt6920:1","description":"Switch Status","format":"bool","access":["read","write","notify"],"unit":"none"},{"iid":2,"type":"urn:miot-spec-v2:property:mode:00000008:rotai-rt6920:1","description":"Mode","format":"uint8","access":["read","write","notify"],"unit":"none","value-list":[{"value":0,"description":"AutoNone"},{"value":1,"description":"SportsRefresh"},{"value":2,"description":"Full Body"},{"value":3,"description":"RestSleep"},{"value":4,"description":"WorkingRelief"},{"value":5,"description":"Shoulder and Neck"},{"value":6,"description":"Waist and Hip"},{"value":7,"description":"ZeroGravity"}]},{"iid":3,"type":"urn:miot-spec-v2:property:status:00000007:rotai-rt6920:1","description":"Status","format":"uint8","access":["read","notify"],"unit":"none","value-list":[{"value":1,"description":"Idle"},{"value":2,"description":"Busy"},{"value":3,"description":"Reset"},{"value":0,"description":"Closed"}]},{"iid":4,"type":"urn:miot-spec-v2:property:fault:00000009:rotai-rt6920:1","description":"Device Fault","format":"uint8","access":["read","notify"],"value-list":[{"value":0,"description":"No Faults"}]},{"iid":5,"type":"urn:miot-spec-v2:property:massage-strength:00000051:rotai-rt6920:1","description":"Massage Strength","format":"uint8","access":["read","write","notify"],"unit":"none","value-range":[0,5,1]},{"iid":6,"type":"urn:miot-spec-v2:property:massage-part:00000050:rotai-rt6920:1","description":"Massage Part","format":"uint8","access":["read","write","notify"],"unit":"none","value-list":[{"value":0,"description":"None"},{"value":1,"description":"Whole"},{"value":2,"description":"Partial"},{"value":3,"description":"Point"}]},{"iid":7,"type":"urn:miot-spec-v2:property:massage-manipulation:0000004F:rotai-rt6920:1","description":"Massage Manipulation","format":"uint8","access":["read","write","notify"],"unit":"none","value-list":[{"value":0,"description":"None"},{"value":1,"description":"Kneading"},{"value":2,"description":"Knocking"},{"value":3,"description":"Tapping"},{"value":4,"description":"Shiatsu"},{"value":5,"description":"Sync"},{"value":6,"description":"ThreeDShiatsu"}]},{"iid":8,"type":"urn:miot-spec-v2:property:left-time:0000003C:rotai-rt6920:1","description":"Left Time","format":"uint16","access":["read","notify"],"unit":"minutes","value-range":[0,1440,1]},{"iid":9,"type":"urn:miot-spec-v2:property:target-position:0000003A:rotai-rt6920:1","description":"Target Position","format":"uint8","access":["read","write","notify"],"unit":"none","value-list":[{"value":0,"description":"Stop"},{"value":1,"description":"MovementUp"},{"value":2,"description":"MovementDown"}]}],"actions":[{"iid":1,"type":"urn:miot-spec-v2:action:stop-massage:0000281F:rotai-rt6920:1","description":"Stop Massage","in":[],"out":[]}]},{"iid":5,"type":"urn:miot-spec-v2:service:backrest-control:0000782A:rotai-rt6920:1","description":"Backrest Control","properties":[{"iid":1,"type":"urn:miot-spec-v2:property:backrest-angle:00000052:rotai-rt6920:1","description":"Backrest Angle","format":"uint8","access":["read","write","notify"],"unit":"none","value-list":[{"value":0,"description":"Stop"},{"value":1,"description":"Up"},{"value":2,"description":"Down"}]},{"iid":2,"type":"urn:miot-spec-v2:property:mode:00000008:rotai-rt6920:1","description":"Mode","format":"uint8","access":["read","write","notify"],"unit":"none","value-list":[{"value":0,"description":"None"},{"value":1,"description":"ZeroGravity"}]}]},{"iid":4,"type":"urn:rotai-spec:service:property-control:00007801:rotai-rt6920:1","description":"property-control","properties":[{"iid":1,"type":"urn:rotai-spec:property:heating-switch:00000001:rotai-rt6920:1","description":"heating-switch","format":"bool","access":["read","notify","write"],"unit":"none"},{"iid":2,"type":"urn:rotai-spec:property:footroller-strength:00000002:rotai-rt6920:1","description":"footroller-strength","format":"uint8","access":["read","notify","write"],"unit":"none","value-range":[0,3,1]},{"iid":3,"type":"urn:rotai-spec:property:gasbag-part:00000003:rotai-rt6920:1","description":"","format":"uint8","access":["read","notify","write"],"unit":"none","value-list":[{"value":1,"description":"全身"},{"value":2,"description":"臂肩"},{"value":3,"description":"腿脚"},{"value":23,"description":"臂肩+腿脚"},{"value":0,"description":"关闭"}]},{"iid":4,"type":"urn:rotai-spec:property:massage-speed:00000004:rotai-rt6920:1","description":"massage-speed","format":"uint8","access":["read","notify","write"],"unit":"none","value-range":[1,6,1]},{"iid":5,"type":"urn:rotai-spec:property:zero-gravity:00000005:rotai-rt6920:1","description":"zero-gravity","format":"bool","access":["read","notify","write"],"unit":"none"},{"iid":6,"type":"urn:rotai-spec:property:gasbag-strength:00000006:rotai-rt6920:1","description":"gasbag-strength","format":"uint8","access":["read","notify","write"],"value-range":[1,5,1]}]}]}